datalad_fuse/__init__.py
datalad_fuse/_version.py
datalad_fuse/consts.py
datalad_fuse/fsspec.py
datalad_fuse/fsspec_cache_clear.py
datalad_fuse/fsspec_head.py
datalad_fuse/fuse_.py
datalad_fuse/utils.py
datalad_fuse/tests/__init__.py
datalad_fuse/tests/conftest.py
datalad_fuse/tests/test_fsspec_head.py
datalad_fuse/tests/test_fuse.py
datalad_fuse/tests/test_util.py
datalad_fuse/tests/data/binary.png
datalad_fuse/tests/data/text.txt
datalad_fuse-0.5.1.dist-info/LICENSE
datalad_fuse-0.5.1.dist-info/METADATA
datalad_fuse-0.5.1.dist-info/WHEEL
datalad_fuse-0.5.1.dist-info/entry_points.txt
datalad_fuse-0.5.1.dist-info/top_level.txt
datalad_fuse-0.5.1.dist-info/RECORD
