Metadata-Version: 2.1
Name: datalad-fuse
Version: 0.5.1
Summary: DataLad FUSE extension package
Home-page: https://github.com/datalad/datalad-fuse
Author: The DataLad Team and Contributors
Author-email: team@datalad.org
License: MIT
Classifier: Programming Language :: Python
Classifier: License :: OSI Approved :: BSD License
Classifier: Programming Language :: Python :: 3
Requires-Python: >=3.7
License-File: LICENSE
Requires-Dist: aiohttp-retry ~=2.8
Requires-Dist: datalad >=0.17.0
Requires-Dist: fsspec[fuse,http] !=2022.10.0,>=2022.1.0
Requires-Dist: methodtools ~=0.4.5
Requires-Dist: typing-extensions ; python_version < "3.10"
Provides-Extra: test
Requires-Dist: coverage ~=6.0 ; extra == 'test'
Requires-Dist: linesep ~=0.2 ; extra == 'test'
Requires-Dist: pytest ; extra == 'test'
Requires-Dist: requests ~=2.20 ; extra == 'test'
